PassGenerated/__init__.py
PassGenerated/password_generator.py
PassGenerated-0.1.4.dist-info/LICENSE
PassGenerated-0.1.4.dist-info/METADATA
PassGenerated-0.1.4.dist-info/WHEEL
PassGenerated-0.1.4.dist-info/top_level.txt
PassGenerated-0.1.4.dist-info/RECORD
