Metadata-Version: 2.1
Name: PassGenerated
Version: 0.1.4
Summary: Lib for generating passwords
Home-page: https://github.com/Liounex/pyLibR.git
Author: JhimmyGC
Author-email: pbbanger32@gmail.com
Classifier: Programming Language :: Python :: 3
Classifier: License :: OSI Approved :: MIT License
Classifier: Operating System :: OS Independent
Requires-Python: >=3.6
License-File: LICENSE
